pymixel/__init__.py
pymixel/address.py
pymixel/dynamixel.py
pymixel-1.0.0.dist-info/LICENSE
pymixel-1.0.0.dist-info/METADATA
pymixel-1.0.0.dist-info/WHEEL
pymixel-1.0.0.dist-info/top_level.txt
pymixel-1.0.0.dist-info/RECORD
