Metadata-Version: 2.1
Name: pymixel
Version: 1.0.0
Summary: Dynamixel X Python Package
Home-page: https://github.com/Vinz1911/Pymixel
Author: Vinzenz Weist
Author-email: Vinz1911@gmail.com
License: GPLv3
Platform: UNKNOWN
Requires-Dist: dynamixel-sdk
